baasWeb/__init__.py
baasWeb/baasAutoWeb.py
baas_web-1.0.8.dist-info/METADATA
baas_web-1.0.8.dist-info/WHEEL
baas_web-1.0.8.dist-info/top_level.txt
baas_web-1.0.8.dist-info/RECORD
